pyfalcon
