Metadata-Version: 1.1
Name: pyfalcon
Version: 1.1.2
Summary: open falcon python client
Home-page: https://github.com/fatelei/pyfalcon
Author: fatelei
Author-email: fatelei@gmail.com
License: BSD License
Platform: UNKNOWN
Classifier: Development Status :: 5 - Production/Stable
Classifier: Environment :: Console
Classifier: Environment :: Web Environment
Classifier: Intended Audience :: Developers
Classifier: License :: OSI Approved :: BSD License
Classifier: Programming Language :: Python :: 2.7
Classifier: Topic :: Software Development :: Libraries
